pyporscheconnectapi/__init__.py
pyporscheconnectapi/account.py
pyporscheconnectapi/cli.py
pyporscheconnectapi/connection.py
pyporscheconnectapi/const.py
pyporscheconnectapi/exceptions.py
pyporscheconnectapi/oauth2.py
pyporscheconnectapi/remote_services.py
pyporscheconnectapi/vehicle.py
pyporscheconnectapi-0.2.4.dist-info/licenses/LICENSE
pyporscheconnectapi-0.2.4.dist-info/METADATA
pyporscheconnectapi-0.2.4.dist-info/WHEEL
pyporscheconnectapi-0.2.4.dist-info/entry_points.txt
pyporscheconnectapi-0.2.4.dist-info/top_level.txt
pyporscheconnectapi-0.2.4.dist-info/RECORD
