Metadata-Version: 2.4
Name: pyporscheconnectapi
Version: 0.2.4
Summary: Python library and CLI for communicating with Porsche Connect API.
Home-page: https://github.com/cjne/pyporscheconnectapi
Author: Johan Isaksson
Author-email: johan@generatorhallen.se
License: MIT
Classifier: License :: OSI Approved :: MIT License
Classifier: Programming Language :: Python
Classifier: Operating System :: OS Independent
Requires-Python: >=3.10
License-File: LICENSE
Requires-Dist: httpx<1
Requires-Dist: BeautifulSoup4
Requires-Dist: rich
Dynamic: author
Dynamic: author-email
Dynamic: classifier
Dynamic: description
Dynamic: description-content-type
Dynamic: home-page
Dynamic: license
Dynamic: license-file
Dynamic: requires-dist
Dynamic: requires-python
Dynamic: summary
